.pylintrc
AUTHORS
ChangeLog
README.md
requirements.txt
setup.cfg
setup.py
YasOpenstackHandler.egg-info/PKG-INFO
YasOpenstackHandler.egg-info/SOURCES.txt
YasOpenstackHandler.egg-info/dependency_links.txt
YasOpenstackHandler.egg-info/not-zip-safe
YasOpenstackHandler.egg-info/pbr.json
YasOpenstackHandler.egg-info/requires.txt
YasOpenstackHandler.egg-info/top_level.txt
etc/yas/openstack.yml
yas_openstack/__init__.py
yas_openstack/configuration.py
yas_openstack/handler.py
yas_openstack/server.py
yas_openstack/yaml_file_config.py